mongo_helper/__init__.py
mongo_helper/collection.py
mongo_helper/queries.py
mongo_helper/settings.ini
tests/__init__.py
tests/test_collection.py
tests/test_crud.py
mongo_helper-0.1.1.dist-info/LICENSE.txt
mongo_helper-0.1.1.dist-info/METADATA
mongo_helper-0.1.1.dist-info/WHEEL
mongo_helper-0.1.1.dist-info/top_level.txt
mongo_helper-0.1.1.dist-info/RECORD
