Metadata-Version: 2.1
Name: mongo-helper
Version: 0.1.1
Summary: Helper funcs and tools for working with MongoDB
Home-page: https://github.com/kenjyco/mongo-helper
Author: Ken
Author-email: kenjyco@gmail.com
License: MIT
Download-URL: https://github.com/kenjyco/mongo-helper/tarball/v0.1.1
Keywords: mongo,mongodb,aggregation pipeline,data,database,helper,kenjyco
Platform: UNKNOWN
Classifier: Development Status :: 4 - Beta
Classifier: Environment :: Console
Classifier: Intended Audience :: Developers
Classifier: License :: OSI Approved :: MIT License
Classifier: Operating System :: MacOS :: MacOS X
Classifier: Operating System :: POSIX :: Linux
Classifier: Programming Language :: Python :: 3.5
Classifier: Programming Language :: Python :: 3.6
Classifier: Programming Language :: Python :: 3.7
Classifier: Programming Language :: Python :: 3.8
Classifier: Programming Language :: Python :: 3.9
Classifier: Programming Language :: Python :: 3.10
Classifier: Programming Language :: Python :: 3.11
Classifier: Programming Language :: Python :: 3.12
Classifier: Programming Language :: Python :: 3.13
Classifier: Programming Language :: Python
Classifier: Topic :: Database
Classifier: Topic :: Software Development :: Libraries
Classifier: Topic :: Utilities
Requires-Dist: dt-helper
Requires-Dist: pymongo>=3.7.2
Requires-Dist: settings-helper
Requires-Dist: pymongo>=3.10.0; python_version >= "3.10"
